setup.py
odoo/addons/knowledge_pages_api/CHANGELOG.md
odoo/addons/knowledge_pages_api/README.rst
odoo/addons/knowledge_pages_api/__init__.py
odoo/addons/knowledge_pages_api/__manifest__.py
odoo/addons/knowledge_pages_api/models/__init__.py
odoo/addons/knowledge_pages_api/models/document_page.py
odoo/addons/knowledge_pages_api/models/knowledge_pages_highlight.py
odoo/addons/knowledge_pages_api/security/ir.model.access.csv
odoo/addons/knowledge_pages_api/services/__init__.py
odoo/addons/knowledge_pages_api/services/page_service.py
odoo/addons/knowledge_pages_api/static/description/icon.png
odoo/addons/knowledge_pages_api/views/knowledge_page_highlight.xml
odoo/addons/knowledge_pages_api/views/knowledge_page_view.xml
odoo_addon_knowledge_pages_api.egg-info/PKG-INFO
odoo_addon_knowledge_pages_api.egg-info/SOURCES.txt
odoo_addon_knowledge_pages_api.egg-info/dependency_links.txt
odoo_addon_knowledge_pages_api.egg-info/not-zip-safe
odoo_addon_knowledge_pages_api.egg-info/requires.txt
odoo_addon_knowledge_pages_api.egg-info/top_level.txt